{
  "name": "odata-ui-grid",
  "description": "odata uiGrid",
  "license": "MIT",
  "keywords": [
    "uiGrid",
    "ngGrid",
    "Odata"
  ],
  "repository": {
    "type": "git",
    "url": "https://github.com/rodrigopivi/odataUiGrid.git"
  },
  "authors": [
    "Rodrigo Pimentel"
  ],
  "main": [
    "dist/odata-ui-grid.js"
  ],
  "private": false,
  "ignore": [
    "bin",
    "lib",
    "demo",
    "vendor",
    "obj",
    "node_modules",
    "**/.*",
    "**/*.csproj",
    "**/*.user",
    "**/*.sln",
    "**/*.html",
    "**/*.config",
    ".bowerrc",
    ".gitignore",
    ".jshintrc",
    "*.json",
    "gulpfile.js",
    "index.html",
    "karma.conf.js",
    "package.json",
    "README.txt"
  ],
  "dependencies": {
    "angular": "~1.4.4",
    "angular-odata-resources": "~1.0.10",
    "angular-ui-grid": "~3.0.5"
  },
  "devDependencies": {
    "bootstrap": "~3.3.5",
    "angular-mocks": "~1.4.4",
    "angular-scenario": "~1.4.4",
    "jasmine": "~2.3.4"
  },
  "homepage": "https://github.com/rodrigopivi/odataUiGrid",
  "_release": "23f5d07260",
  "_resolution": {
    "type": "branch",
    "branch": "master",
    "commit": "23f5d072605ef562e0688a2ce66bfa6413d7f93e"
  },
  "_source": "https://github.com/rodrigopivi/odataUiGrid.git",
  "_target": "*",
  "_originalSource": "odata-ui-grid"
}